millilensing/.version
millilensing/__init__.py
millilensing/prior.py
millilensing/source.py
millilensing/waveform_generator.py
millilensing-0.0.1.dist-info/LICENSE
millilensing-0.0.1.dist-info/METADATA
millilensing-0.0.1.dist-info/WHEEL
millilensing-0.0.1.dist-info/top_level.txt
millilensing-0.0.1.dist-info/RECORD
