Metadata-Version: 2.1
Name: millilensing
Version: 0.0.1
Summary: Millilensing
Home-page: https://git.ligo.org/ania.liu/millilensing
Author: Ania Liu
License: MIT
Classifier: Programming Language :: Python :: 3.6
Classifier: Programming Language :: Python :: 3.7
Classifier: Programming Language :: Python :: 3.8
Classifier: License :: OSI Approved :: MIT License
Classifier: Operating System :: OS Independent
Requires-Python: >=3.5
License-File: LICENSE
Requires-Dist: bilby
Requires-Dist: lalsuite
Requires-Dist: numpy (>=1.9)
